<?xml version="1.0" encoding="UTF-8" standalone="yes"?>
<p:sldLayout xmlns:a="http://schemas.openxmlformats.org/drawingml/2006/main" xmlns:r="http://schemas.openxmlformats.org/officeDocument/2006/relationships" xmlns:p="http://schemas.openxmlformats.org/presentationml/2006/main" type="twoTxTwoObj" preserve="1"><p:cSld name="Comparação"><p:spTree><p:nvGrpSpPr><p:cNvPr id="1" name=""/><p:cNvGrpSpPr/><p:nvPr/></p:nvGrpSpPr><p:grpSpPr><a:xfrm><a:off x="0" y="0"/><a:ext cx="0" cy="0"/><a:chOff x="0" y="0"/><a:chExt cx="0" cy="0"/></a:xfrm></p:grpSpPr><p:sp><p:nvSpPr><p:cNvPr id="2" name="Título 1"><a:extLst><a:ext uri="{FF2B5EF4-FFF2-40B4-BE49-F238E27FC236}"><a16:creationId xmlns:a16="http://schemas.microsoft.com/office/drawing/2014/main" id="{D5F90D6B-C876-4F08-B2CF-90AB899A768B}"/></a:ext></a:extLst></p:cNvPr><p:cNvSpPr><a:spLocks noGrp="1"/></p:cNvSpPr><p:nvPr><p:ph type="title"/></p:nvPr></p:nvSpPr><p:spPr><a:xfrm><a:off x="839788" y="365125"/><a:ext cx="10515600" cy="1325563"/></a:xfrm></p:spPr><p:txBody><a:bodyPr/><a:lstStyle/><a:p><a:r><a:rPr lang="pt-BR"/><a:t>Clique para editar o título Mestre</a:t></a:r></a:p></p:txBody></p:sp><p:sp><p:nvSpPr><p:cNvPr id="3" name="Espaço Reservado para Texto 2"><a:extLst><a:ext uri="{FF2B5EF4-FFF2-40B4-BE49-F238E27FC236}"><a16:creationId xmlns:a16="http://schemas.microsoft.com/office/drawing/2014/main" id="{415FB6B5-C884-467E-8143-F40307AD0402}"/></a:ext></a:extLst></p:cNvPr><p:cNvSpPr><a:spLocks noGrp="1"/></p:cNvSpPr><p:nvPr><p:ph type="body" idx="1"/></p:nvPr></p:nvSpPr><p:spPr><a:xfrm><a:off x="839788" y="1681163"/><a:ext cx="5157787" cy="823912"/></a:xfrm></p:spPr><p:txBody><a:bodyPr anchor="b"/><a:lstStyle><a:lvl1pPr marL="0" indent="0"><a:buNone/><a:defRPr sz="2400" b="1"/></a:lvl1pPr><a:lvl2pPr marL="457200" indent="0"><a:buNone/><a:defRPr sz="2000" b="1"/></a:lvl2pPr><a:lvl3pPr marL="914400" indent="0"><a:buNone/><a:defRPr sz="1800" b="1"/></a:lvl3pPr><a:lvl4pPr marL="1371600" indent="0"><a:buNone/><a:defRPr sz="1600" b="1"/></a:lvl4pPr><a:lvl5pPr marL="1828800" indent="0"><a:buNone/><a:defRPr sz="1600" b="1"/></a:lvl5pPr><a:lvl6pPr marL="2286000" indent="0"><a:buNone/><a:defRPr sz="1600" b="1"/></a:lvl6pPr><a:lvl7pPr marL="2743200" indent="0"><a:buNone/><a:defRPr sz="1600" b="1"/></a:lvl7pPr><a:lvl8pPr marL="3200400" indent="0"><a:buNone/><a:defRPr sz="1600" b="1"/></a:lvl8pPr><a:lvl9pPr marL="3657600" indent="0"><a:buNone/><a:defRPr sz="1600" b="1"/></a:lvl9pPr></a:lstStyle><a:p><a:pPr lvl="0"/><a:r><a:rPr lang="pt-BR"/><a:t>Clique para editar os estilos de texto Mestres</a:t></a:r></a:p></p:txBody></p:sp><p:sp><p:nvSpPr><p:cNvPr id="4" name="Espaço Reservado para Conteúdo 3"><a:extLst><a:ext uri="{FF2B5EF4-FFF2-40B4-BE49-F238E27FC236}"><a16:creationId xmlns:a16="http://schemas.microsoft.com/office/drawing/2014/main" id="{E94C612C-92BB-4C22-88A4-8A800BFEC78F}"/></a:ext></a:extLst></p:cNvPr><p:cNvSpPr><a:spLocks noGrp="1"/></p:cNvSpPr><p:nvPr><p:ph sz="half" idx="2"/></p:nvPr></p:nvSpPr><p:spPr><a:xfrm><a:off x="839788" y="2505075"/><a:ext cx="5157787" cy="3684588"/></a:xfrm></p:spPr><p:txBody><a:bodyPr/><a:lstStyle/><a:p><a:pPr lvl="0"/><a:r><a:rPr lang="pt-BR"/><a:t>Clique para editar os estilos de texto Mestres</a:t></a:r></a:p><a:p><a:pPr lvl="1"/><a:r><a:rPr lang="pt-BR"/><a:t>Segundo nível</a:t></a:r></a:p><a:p><a:pPr lvl="2"/><a:r><a:rPr lang="pt-BR"/><a:t>Terceiro nível</a:t></a:r></a:p><a:p><a:pPr lvl="3"/><a:r><a:rPr lang="pt-BR"/><a:t>Quarto nível</a:t></a:r></a:p><a:p><a:pPr lvl="4"/><a:r><a:rPr lang="pt-BR"/><a:t>Quinto nível</a:t></a:r></a:p></p:txBody></p:sp><p:sp><p:nvSpPr><p:cNvPr id="5" name="Espaço Reservado para Texto 4"><a:extLst><a:ext uri="{FF2B5EF4-FFF2-40B4-BE49-F238E27FC236}"><a16:creationId xmlns:a16="http://schemas.microsoft.com/office/drawing/2014/main" id="{867B6DD6-9AF8-453F-BEB6-7D5CF8113962}"/></a:ext></a:extLst></p:cNvPr><p:cNvSpPr><a:spLocks noGrp="1"/></p:cNvSpPr><p:nvPr><p:ph type="body" sz="quarter" idx="3"/></p:nvPr></p:nvSpPr><p:spPr><a:xfrm><a:off x="6172200" y="1681163"/><a:ext cx="5183188" cy="823912"/></a:xfrm></p:spPr><p:txBody><a:bodyPr anchor="b"/><a:lstStyle><a:lvl1pPr marL="0" indent="0"><a:buNone/><a:defRPr sz="2400" b="1"/></a:lvl1pPr><a:lvl2pPr marL="457200" indent="0"><a:buNone/><a:defRPr sz="2000" b="1"/></a:lvl2pPr><a:lvl3pPr marL="914400" indent="0"><a:buNone/><a:defRPr sz="1800" b="1"/></a:lvl3pPr><a:lvl4pPr marL="1371600" indent="0"><a:buNone/><a:defRPr sz="1600" b="1"/></a:lvl4pPr><a:lvl5pPr marL="1828800" indent="0"><a:buNone/><a:defRPr sz="1600" b="1"/></a:lvl5pPr><a:lvl6pPr marL="2286000" indent="0"><a:buNone/><a:defRPr sz="1600" b="1"/></a:lvl6pPr><a:lvl7pPr marL="2743200" indent="0"><a:buNone/><a:defRPr sz="1600" b="1"/></a:lvl7pPr><a:lvl8pPr marL="3200400" indent="0"><a:buNone/><a:defRPr sz="1600" b="1"/></a:lvl8pPr><a:lvl9pPr marL="3657600" indent="0"><a:buNone/><a:defRPr sz="1600" b="1"/></a:lvl9pPr></a:lstStyle><a:p><a:pPr lvl="0"/><a:r><a:rPr lang="pt-BR"/><a:t>Clique para editar os estilos de texto Mestres</a:t></a:r></a:p></p:txBody></p:sp><p:sp><p:nvSpPr><p:cNvPr id="6" name="Espaço Reservado para Conteúdo 5"><a:extLst><a:ext uri="{FF2B5EF4-FFF2-40B4-BE49-F238E27FC236}"><a16:creationId xmlns:a16="http://schemas.microsoft.com/office/drawing/2014/main" id="{AF7BC43A-746B-4A81-875D-5A6A3218CC61}"/></a:ext></a:extLst></p:cNvPr><p:cNvSpPr><a:spLocks noGrp="1"/></p:cNvSpPr><p:nvPr><p:ph sz="quarter" idx="4"/></p:nvPr></p:nvSpPr><p:spPr><a:xfrm><a:off x="6172200" y="2505075"/><a:ext cx="5183188" cy="3684588"/></a:xfrm></p:spPr><p:txBody><a:bodyPr/><a:lstStyle/><a:p><a:pPr lvl="0"/><a:r><a:rPr lang="pt-BR"/><a:t>Clique para editar os estilos de texto Mestres</a:t></a:r></a:p><a:p><a:pPr lvl="1"/><a:r><a:rPr lang="pt-BR"/><a:t>Segundo nível</a:t></a:r></a:p><a:p><a:pPr lvl="2"/><a:r><a:rPr lang="pt-BR"/><a:t>Terceiro nível</a:t></a:r></a:p><a:p><a:pPr lvl="3"/><a:r><a:rPr lang="pt-BR"/><a:t>Quarto nível</a:t></a:r></a:p><a:p><a:pPr lvl="4"/><a:r><a:rPr lang="pt-BR"/><a:t>Quinto nível</a:t></a:r></a:p></p:txBody></p:sp><p:sp><p:nvSpPr><p:cNvPr id="7" name="Espaço Reservado para Data 6"><a:extLst><a:ext uri="{FF2B5EF4-FFF2-40B4-BE49-F238E27FC236}"><a16:creationId xmlns:a16="http://schemas.microsoft.com/office/drawing/2014/main" id="{F718A3E3-BDAE-4A0A-9BD4-4436C9013525}"/></a:ext></a:extLst></p:cNvPr><p:cNvSpPr><a:spLocks noGrp="1"/></p:cNvSpPr><p:nvPr><p:ph type="dt" sz="half" idx="10"/></p:nvPr></p:nvSpPr><p:spPr/><p:txBody><a:bodyPr/><a:lstStyle/><a:p><a:fld id="{AD9E9694-E0B5-4766-817A-4A2B8E6081E6}" type="datetimeFigureOut"><a:rPr lang="pt-BR" smtClean="0"/><a:t>22/08/2025</a:t></a:fld><a:endParaRPr lang="pt-BR"/></a:p></p:txBody></p:sp><p:sp><p:nvSpPr><p:cNvPr id="8" name="Espaço Reservado para Rodapé 7"><a:extLst><a:ext uri="{FF2B5EF4-FFF2-40B4-BE49-F238E27FC236}"><a16:creationId xmlns:a16="http://schemas.microsoft.com/office/drawing/2014/main" id="{750E05E2-4247-4E84-B00C-FC9CD3F71066}"/></a:ext></a:extLst></p:cNvPr><p:cNvSpPr><a:spLocks noGrp="1"/></p:cNvSpPr><p:nvPr><p:ph type="ftr" sz="quarter" idx="11"/></p:nvPr></p:nvSpPr><p:spPr/><p:txBody><a:bodyPr/><a:lstStyle/><a:p><a:endParaRPr lang="pt-BR"/></a:p></p:txBody></p:sp><p:sp><p:nvSpPr><p:cNvPr id="9" name="Espaço Reservado para Número de Slide 8"><a:extLst><a:ext uri="{FF2B5EF4-FFF2-40B4-BE49-F238E27FC236}"><a16:creationId xmlns:a16="http://schemas.microsoft.com/office/drawing/2014/main" id="{2A2C4FED-3427-4452-801F-4ECC3045BA7B}"/></a:ext></a:extLst></p:cNvPr><p:cNvSpPr><a:spLocks noGrp="1"/></p:cNvSpPr><p:nvPr><p:ph type="sldNum" sz="quarter" idx="12"/></p:nvPr></p:nvSpPr><p:spPr/><p:txBody><a:bodyPr/><a:lstStyle/><a:p><a:fld id="{6BC802F2-4E3A-464C-A672-D321C39BF870}" type="slidenum"><a:rPr lang="pt-BR" smtClean="0"/><a:t>‹nº›</a:t></a:fld><a:endParaRPr lang="pt-BR"/></a:p></p:txBody></p:sp></p:spTree><p:extLst><p:ext uri="{BB962C8B-B14F-4D97-AF65-F5344CB8AC3E}"><p14:creationId xmlns:p14="http://schemas.microsoft.com/office/powerpoint/2010/main" val="1269015418"/></p:ext></p:extLst></p:cSld><p:clrMapOvr><a:masterClrMapping/></p:clrMapOvr></p:sldLayout>